strands_sglang/__init__.py
strands_sglang/client.py
strands_sglang/sglang.py
strands_sglang/token.py
strands_sglang/tool_limiter.py
strands_sglang/tool_parser.py
strands_sglang-0.0.3.dist-info/METADATA
strands_sglang-0.0.3.dist-info/WHEEL
strands_sglang-0.0.3.dist-info/licenses/LICENSE
strands_sglang-0.0.3.dist-info/RECORD
