Metadata-Version: 2.4
Name: strands-sglang
Version: 0.0.3
Summary: SGLang model provider for Strands Agents SDK with Token-In/Token-Out (TITO) support for agentic RL training.
Project-URL: Homepage, https://github.com/horizon-rl/strands-sglang/
Project-URL: Documentation, https://github.com/horizon-rl/strands-sglang/#readme
Project-URL: Repository, https://github.com/horizon-rl/strands-sglang/
Project-URL: Issues, https://github.com/horizon-rl/strands-sglang/issues
Author-email: Yuan He <yuanhe.cs.ai@gmail.com>
License-Expression: Apache-2.0
License-File: LICENSE
Keywords: agentic-rl,agents,ai,llm,reinforcement-learning,rl,sglang,strands
Classifier: Development Status :: 3 - Alpha
Classifier: Intended Audience :: Developers
Classifier: Intended Audience :: Science/Research
Classifier: License :: OSI Approved :: Apache Software License
Classifier: Programming Language :: Python :: 3
Classifier: Programming Language :: Python :: 3.10
Classifier: Programming Language :: Python :: 3.11
Classifier: Programming Language :: Python :: 3.12
Classifier: Topic :: Scientific/Engineering :: Artificial Intelligence
Classifier: Topic :: Software Development :: Libraries :: Python Modules
Requires-Python: >=3.10
Requires-Dist: httpx
Requires-Dist: openai
Requires-Dist: strands-agents
Requires-Dist: transformers
Provides-Extra: aws
Requires-Dist: bedrock-agentcore; extra == 'aws'
Provides-Extra: dev
Requires-Dist: build>=0.10.0; extra == 'dev'
Requires-Dist: ipykernel>=7.1.0; extra == 'dev'
Requires-Dist: pre-commit; extra == 'dev'
Requires-Dist: pytest-asyncio>=0.21.0; extra == 'dev'
Requires-Dist: pytest-cov>=4.0.0; extra == 'dev'
Requires-Dist: pytest-mock>=3.0.0; extra == 'dev'
Requires-Dist: pytest>=7.0.0; extra == 'dev'
Requires-Dist: ruff>=0.1.0; extra == 'dev'
Requires-Dist: strands-agents-tools; extra == 'dev'
Requires-Dist: twine>=4.0.0; extra == 'dev'
